MANIFEST.in
README.md
requirements.txt
setup.py
src/chai_guanaco/__init__.py
src/chai_guanaco/chat.py
src/chai_guanaco/feedback.py
src/chai_guanaco/formatters.py
src/chai_guanaco/login_cli.py
src/chai_guanaco/metrics.py
src/chai_guanaco/submit.py
src/chai_guanaco/utils.py
src/chai_guanaco/resources/bot_config/blade.json
src/chai_guanaco/resources/bot_config/captain_wyatt.json
src/chai_guanaco/resources/bot_config/coffee_shop_girl.json
src/chai_guanaco/resources/bot_config/filbert.json
src/chai_guanaco/resources/bot_config/leo.json
src/chai_guanaco/resources/bot_config/levi.json
src/chai_guanaco/resources/bot_config/mr_wilson.json
src/chai_guanaco/resources/bot_config/nerd_girl.json
src/chai_guanaco/resources/bot_config/scaramouche.json
src/chai_guanaco/resources/bot_config/story_teller.json
src/chai_guanaco/resources/bot_config/vampire_queen.json
src/chai_guanaco/resources/bot_config/wednesday_addams.json
src/chai_guanaco_private/__init__.py
src/chai_guanaco_private/submit_blend.py
src/openchai.egg-info/PKG-INFO
src/openchai.egg-info/SOURCES.txt
src/openchai.egg-info/dependency_links.txt
src/openchai.egg-info/entry_points.txt
src/openchai.egg-info/not-zip-safe
src/openchai.egg-info/requires.txt
src/openchai.egg-info/top_level.txt
tests/test_chai_guanaco/test_chat.py
tests/test_chai_guanaco/test_feedback.py
tests/test_chai_guanaco/test_guanaco_python_utils.py
tests/test_chai_guanaco/test_login.py
tests/test_chai_guanaco/test_metrics.py
tests/test_chai_guanaco/test_submit.py
tests/test_chai_guanaco/resources/test_get_leaderboard.yaml
tests/test_chai_guanaco/resources/test_get_submission_metrics.yaml
tests/test_chai_guanaco_private/test_submit_blend.py