Metadata-Version: 2.1
Name: openchai
Version: 0.0.0
Summary: Open Chai
Home-page: https://www.open-chai.com
Author: Chai Research Corp.
Author-email: hello@chai-research.com
License: MIT
Platform: UNKNOWN
